dbdb/__init__.py
dbdb/dbdb_project.py
tinydbdb-1.0.1.dist-info/licenses/LICENSE
tinydbdb-1.0.1.dist-info/METADATA
tinydbdb-1.0.1.dist-info/WHEEL
tinydbdb-1.0.1.dist-info/entry_points.txt
tinydbdb-1.0.1.dist-info/top_level.txt
tinydbdb-1.0.1.dist-info/RECORD
