Metadata-Version: 2.4
Name: tinydbdb
Version: 1.0.1
Summary: A simple file-based key-value database with CLI and persistence
Author-email: Vikas Gulia <vikasgulia17@example.com>
License: MIT License
Keywords: database,key-value,cli,pickle,educational
Classifier: Programming Language :: Python :: 3
Classifier: Programming Language :: Python :: 3.9
Classifier: Programming Language :: Python :: 3.10
Classifier: Programming Language :: Python :: 3.11
Classifier: Programming Language :: Python :: 3.12
Classifier: License :: OSI Approved :: MIT License
Classifier: Operating System :: OS Independent
Requires-Python: >=3.9
License-File: LICENSE
Dynamic: license-file
